{
  "legajo_id": "41",
  "id_carta": "7410",
  "order_in_legajo": 139,
  "signatura": "089:36",
  "nombre_carta": "Carta de Pedro Santacilia y Pax a Persona desconocida",
  "fecha_original": "15 de agosto de 1647",
  "lugar": "Mallorca",
  "remitente": "Pedro Santacilia y Pax",
  "destinatario": "Persona desconocida",
  "temas": [],
  "idioma": "",
  "resumen": "",
  "modernizada": [
    "don Pedro rodriges muñosfue alferes del Tersio quelleuante el año pasado paraTarragona es moso de muibuena sangre y tiene ualory espiritu de grandes esper-ransas, aplico a uexcelencia ?? le man-de onrar con su sueldo puessabra mereser majores pues:tos con sus acciones que estandobaxo la obediencia de vexcelencia^y jo lo hago por auerme lopedido un tio mio seeruicio ?? destaSanta ?? inquision y ??(^que) es lo que mas deseamos todas las etxuras de uexcelenciacomo ?? que dios nos guardemallorca 15 Agosto 1647Don Pedro Santacilia y Pax^mi Señor [1§] Transcripción literal"
  ],
  "literal": [
    "1. don Pedro rodriges muños2. fue alferes del Tersio que3. lleuante el año pasado para4. Tarragona es moso de mui5. buena sangre y tiene ualor6. y espiritu de grandes esper-7. ransas, aplico a uex< celenci>a [??] le man-8. de onrar con su sueldo pues9. sabra mereser majores pues:10. tos con sus acciones q< ue> estando11. baxo la obediencia de vex< celenci>a12. [^y jo lo hago por auerme lo13. pedido un tio mio seer< uici>o [??] desta14. S< ant>a [??] inquision y [??]]15. (^que) es lo que mas deseamos 16. todas las etxuras de uex< celenci>a17. como [??] que dios nos g< uar>de18. mallorca 15 Agosto 164719. Don Pedro S< ant>acilia y Pax20. [^mi S< eñ>or] [☞]"
  ],
  "imagenes": [
    {
      "filename": "089:36.JPG",
      "original_url": "http://santacilia.info/intranet2/img/Legajo41/089:36.JPG",
      "url": "/legajos/legajo-41/images/089:36.JPG"
    }
  ],
  "has_images": true,
  "primary_image": "089:36.JPG",
  "warnings": [],
  "raw_source": "raw/legajos/legajo-41/cartas/007410.json",
  "primary_image_url": "/legajos/legajo-41/images/089:36.JPG"
}