{
  "legajo_id": "21",
  "id_carta": "3542",
  "order_in_legajo": 231,
  "signatura": "418:5830a.JPG",
  "nombre_carta": "Carta de Jaume Mesquida a Pedro Santacilia y Pax",
  "fecha_original": "6 de enero de 1644",
  "lugar": "Mallorca",
  "remitente": "Jaume Mesquida",
  "destinatario": "Pedro Santacilia y Pax",
  "temas": [],
  "idioma": "",
  "resumen": "",
  "modernizada": [
    "Sior mío con la confianza que siempre he subido y tengo con v. m. me obliga a suplicarle me fovorezca con su poder y amigos en darme un {CAT. advocado} que me defienda en la pretensión que tengo en Son Romaguera por cuando murió mi hermano a [?] y el do sor no la he pedido y ahora me toca a mi. Yo me hallo forastero y faltándome v. m. a quien toda mi vida he subido por señor mío y como hay algunas caballeros los qualles dan su vida, noticia que yo en Itallia Sr. don Pedro Santacilia [1§] era de ella parte y hallándoles en España he sabido que información al doctor Guells quisiere la plaza de mi hermano que no convenía que me diesen lugar que pusiese pleito con mis sobrinas yo me hallo pobre y cargado con 6 iras y pido justicia y si v. m. me encomienda en algún {CAT. advocado} bueno sin duda yo me veré servidor de Son Romaguera y viéndome señor del pondré las órdenes de v. m. como señor mío que es en mi corazón. No tengo sino a v. m. a quien Dios guarde los años de su deseo, de Mallorca y enero a 6 a 1644. Servidor de v. m. Jaime Mesquida Transcripción literal"
  ],
  "literal": [
    "1. Sjor mjo 2. Con la confiansa que siempre 3. e subido i tengo con vm 4. me hubliga asuplicarlle 5. me afovoresca con suyo dor 6. y amigos en darme un at7. vocado que me defenda 8. en la pretension que tengo 9. en son romaguera por 10. quando murio mjermano a11. dres y el do sor nola pedi12. do jagora metoca ami jo 13. meallo forastero y faltandome 14. vm aqujen toda mj vjda esubi15. do por sejor mjo y como ai al16. gunes cavalleres les qualles an su17. bida notisia que jo en itallia 18. [Margen izquierdo][^ Sor do pedro santasilia] [☞]"
  ],
  "imagenes": [
    {
      "filename": "418:5830a.JPG",
      "original_url": "http://santacilia.info/intranet2/img/Legajo21/418:5830a.JPG",
      "url": "/legajos/legajo-21/images/418:5830a.JPG"
    },
    {
      "filename": "419:5830b.JPG",
      "original_url": "http://santacilia.info/intranet2/img/Legajo21/419:5830b.JPG",
      "url": "/legajos/legajo-21/images/419:5830b.JPG"
    }
  ],
  "has_images": true,
  "primary_image": "418:5830a.JPG",
  "warnings": [],
  "raw_source": "raw/legajos/legajo-21/cartas/003542.json",
  "primary_image_url": "/legajos/legajo-21/images/418:5830a.JPG"
}