{
  "legajo_id": "33",
  "id_carta": "4894",
  "order_in_legajo": 89,
  "signatura": "140:6810.JPG",
  "nombre_carta": "Carta de Onofre Morrelles a Pedro Santacilia y Pax",
  "fecha_original": "9 de septiembre de 1630",
  "lugar": "Mallorca",
  "remitente": "Onofre Morrelles",
  "destinatario": "Pedro Santacilia y Pax",
  "temas": [],
  "idioma": "",
  "resumen": "",
  "modernizada": [
    "Amb dos de v. m. em troba a les quals respondré amb esta tinc escrit tot el que em diu i així dic a v. m. quant a lo [?] de lo del fadrí que amb això fas jo solament el que tinc obligació i així no te v. m. perquè fer serimonias puix jo mai les he fetes amb v. m. jo entenc que ell farà com qui es sols me desagrada un poc d'anar de nits que en fi és cosa que aporta en si la jovintut tot per [?] de lo del arcabus com digui a v. m. a l'altre em fa falta i si juntament amb equeix v. m. en trobàs un patit que fos mes avantatjat per butxaca em farà mercè comprar-lo i prendre diners del patró Sagui o de qui v. m. manarà i treuramo a pagar i servesques v. m. fer fer clau en el que te ahir perquè jo la parduda del que diu que te ten tasions de venir v. m. ja sap que jo la de v. m. i que contestant quant tinc i així estarem aparellat a [?] del dames no tinc de que avisar-lo sols lo suplico me'l faci en fer [?] el que diuen per ací de la pèrdua dels tres tercios d'infantaria espanyola si es ver i guardi Nre. Sr. a v. m. com pot i jo desigo de Mallorca i setembre a 9 1630 Onofre Morrelles thezorer i canonge Sr. don Pedro Santacilia i Pax [1§] Transcripción literal"
  ],
  "literal": [
    "1. Ab dos de Vm. em troba a las quals respond[r]e ab2. esta tinc scrit tot lo quem diu y axi dich 3. a V.m. quant a lo [?] de lo del fadrí que ab4. axo fas io solament lo que tinch obbligacio5. Y axi no te Vm p[er] que fer serimonias puis io6. mai las he fetes ab V.m. jo entench quell7. fara com qui es sols me desagrada un poch 8. de enar de nits que en fi es cosa que aporta9. en si la jovintut tot p[er] [?] de lo del10. arcabus com digui a V.m. a laltre em fa falte11. y si juntament ab equex V.m. en trobas un12. patit que fos mes avantatjat p[er] butxaca13. em fara m[erce]d comprarlo y pendre dines del patro14. Sagui o de qui V.m. manara y treuramo a pagar15. y servesques V.m. fer fer clau en el que te ahí16. p[er]que io le parduda de lo que diu que te ten17. tassions de venir V.m. ja sap que io la de18. V.m. y q[ue] contestant quant tinch Y axi19. estare[m] aparellat a [?] del dames20. no tinch de que avisarlo sols lo suplico21. lem fassa en fer [?] lo que diuen22. p[er] aci de la perdua dels tres tercios de23. infantaria española si es ver y gde Nro.24. Sr. a V.m. com pot y io desigo de Mall[or]ca25. y sett[embr]e a 9 163026. Honofre Morrelles thezorer y canonge27. Sr. don Pº Sta. Cilia y Pax [☞]"
  ],
  "imagenes": [
    {
      "filename": "140:6810.JPG",
      "original_url": "http://santacilia.info/intranet2/img/Legajo33/140:6810.JPG",
      "url": "/legajos/legajo-33/images/140:6810.JPG"
    }
  ],
  "has_images": true,
  "primary_image": "140:6810.JPG",
  "warnings": [],
  "raw_source": "raw/legajos/legajo-33/cartas/004894.json",
  "primary_image_url": "/legajos/legajo-33/images/140:6810.JPG"
}