{
  "legajo_id": "27",
  "id_carta": "4631",
  "order_in_legajo": 99,
  "signatura": "173:4440.JPG",
  "nombre_carta": "Carta de Jeroni de Torres a Pedro Santacilia y Pax",
  "fecha_original": "3 de julio de 1647",
  "lugar": "Tarragona",
  "remitente": "Jeroni de Torres",
  "destinatario": "Pedro Santacilia y Pax",
  "temas": [],
  "idioma": "",
  "resumen": "",
  "modernizada": [
    "Haver conegut en v. m. la part de fer mercè a sos servidors [?] jo [?] dels més aficionats que [?] vim a tenir {ESP. alientos} de suplicar-li el que se m'ofereix. El marques d'Aytona m'ha fet mercè d'una conpanyia de Caracas en esta vila [?] de Tarragona de la qual era capità Xitxo Puça, era trompeta de sa companyia un minyó natural de Valls el qual se n'ana en companyia de [?] don Vicens Tutavila [?] a Itàlia esta última vegada han Le sobret que està en la ciutat i per necessitar d'ell i saber que v. m. me farà mercè li suplica [?] treball en parlar [?] abera [?] aseat {ESP. medi} perquè ell to [?] a esta plaça que per a mi és de molta conveniència tenint per major el manar-me v. m. moltes coses de son gust. Déu a v. m. guardi. Tarragona i juliol a 3 1647. Son major servidor i amic v. m. Don Jeroni de Torres Sr. don Pedro Santicilia Transcripción literal"
  ],
  "literal": [
    "1. Lo haver conegut en vm lapa[re?]/2. ce fer merce a sos servidors e[ ??]/3. io h[u?] dels mes afficionats que [illegible]4. vim atenir alientos de suplicarle lo5. que sem offerex. Lo Sr. marques de6. Aytona me ha fet merce de una con/7. panyia de Caracas en esta si la [?]8. de taragona de la qual era capita9. Xitxo Puca, era trompeta de sa con/10. panyia un minyo natural de Valls11. loqual sen ana en companyia de [ ]12. Don Vicens Tutavila [illegible] [illegible]13. a Italia esta ultima vegada an14. Le sobret que esta en la Ciutat15. y per necessitar dell y saber que16. vm me fara merce li suplica17. puerya treball en por [lar?] [abera?]18. asseat medi peraque ell to [n?]e a19. esta plaça que perami es de mol=20. ta conveniencia tenint per ma=21. jor lo manarme vm moltes coses de22. son gust deu a vm ge Taragona23. y Juliol a 3 164724. Son Mayor Seu y amic Vm25. Don Geronymde Torres26. [36, extrem inferior esquerre] Sr. don Pedro Santicilia [☞]"
  ],
  "imagenes": [
    {
      "filename": "173:4440.JPG",
      "original_url": "http://santacilia.info/intranet2/img/Legajo27/173:4440.JPG",
      "url": "/legajos/legajo-27/images/173:4440.JPG"
    }
  ],
  "has_images": true,
  "primary_image": "173:4440.JPG",
  "warnings": [],
  "raw_source": "raw/legajos/legajo-27/cartas/004631.json",
  "primary_image_url": "/legajos/legajo-27/images/173:4440.JPG"
}