{
  "legajo_id": "25",
  "id_carta": "4093",
  "order_in_legajo": 27,
  "signatura": "052_127.JPG",
  "nombre_carta": "Carta de Juan Francisco Pueyo y Clavería a Jerónimo Pelegrín de Aragüés",
  "fecha_original": "30 de marzo de 1667",
  "lugar": "Madrid",
  "remitente": "Juan Francisco Pueyo y Clavería",
  "destinatario": "Jerónimo Pelegrín de Aragüés",
  "temas": [],
  "idioma": "",
  "resumen": "",
  "modernizada": [
    "Sr. mío. He recibido la de v. m. de 12 de febrero con la segunda letra de los 250 reales de plata doble, de lo procedido de esas dos alcaidías, las cuales ya tenía cobrados con la primera, y entregados a mi hermana y avisado a v. m. De todo ahora repito lo mismo, y con la primera ocasión remitiré a v. m. recibo de mi hermana para su resguardo y mío. Muy mal procede Pedro Martorell, pues con tanta razón como tenemos no acaba de pagar y así es necesario que v. m. tome con el la resolución que conviene, que es vergüenza se burle de nosotros, y así v. m. lo haga y si conviniere dar cuenta al virrey lo haga diciendo es cosa mía, que yo sé que nos hará merced. Ya tengo escrito al Dr. Armella sobre esa cobranza de Fortuny y ahora hago lo mismo y también a D. Francisco Pueyo, que yo no sé como son los amigos, que con descuido toman estas cosas, pues yo acá en lo que me toca lo hago con cuidado y brevedad y si fueran como v. m. ya estuviera esto cobrado. El Sr. D. Miguel Salva trata ya de su jornada, y v. m. esté sin cuidado, que irá muy recomendado para que favorezca a v. m. a quien suplico no deje de mandarme en cuanto se le ofrezca, pues sabe mi voluntad y obligación. Guarde Dios a v. m. muchos años como deseo. Madrid y marzo a 30 de 1667. Besa la mano de v. m. su Amigo y servidorD. Francisco de Pueyo y Claveria Sr. don Jeronimo Pelegrin y Aragues Transcripción literal"
  ],
  "literal": [
    "1. Sr. mio He recivido la de Vm. de 12 de Febrero con la2. segunda letra de los 250 Rs. de plata doble, de lo procedido3. deesas dos Alcaydias, las quales ya tenia cobrados con la4. primera, y entregados a mi Herm[an]a y avisado a Vm. de todo 5. agora repito lo mismo, y con la primera occa[sio]n remittire a V.m.6. recivo de mi hermana pª su resguardo y mio.7. Muy mal procede Pedro Martorell, pues con tanta razon como8. tenemos no acava de pagar y assi es necessº que V.m. tome9. con el la resolucion que conviene, que es verguenza se10. burle de nosotros, y assi V.m. lo haga y si conviniere dar qta11. al Sr. Virrey lo haga diciendo es cossa mia, que yo se que nos12. hara m[erce]d.13. Ya tengo escrito al Dr. Armella sobre esa cobranza de Fortuny14. y agora hago lo mismo y tambien a d. Franco. Pueyo, que yo15. no se como son los Amigos, que con descuido toman estas cossas16. pues yo aca en lo que me toca lo hago con cuidado y brevedad17. y si fueran como V.m. ya estubiera esto cobrado.18. El Sr. D. Mig[ue]l Salbe trata ya de su jornada, y V.m. este sin19. cuidado, que ira muy recomendado pª que favorezca a20. V.m. a quien supp[li]co no deje de mandarme en quanto se le21. ofreca, pues save mi voluntad y oblig[acio]n gde Dios a Vm.22. m[ucho]s a[ño]s como deseo, Ma[dri]d y Marzo a 30 de 166723. B.l.m. de V.m.24. Su Amigo y s[ervido]r25. D. Franco. de Pueyo y Claveria26. Sr. Don Gerº Pelegrin y Aragues [☞]"
  ],
  "imagenes": [
    {
      "filename": "052_127.JPG",
      "original_url": "http://santacilia.info/intranet2/img/Legajo25/052_127.JPG",
      "url": "/legajos/legajo-25/images/052_127.JPG"
    }
  ],
  "has_images": true,
  "primary_image": "052_127.JPG",
  "warnings": [
    {
      "code": "SUSPICIOUS_ENCODING_AUX_IFRAME",
      "message": "Se detectaron caracteres sospechosos en metadatos secundarios (5)",
      "context": {}
    }
  ],
  "raw_source": "raw/legajos/legajo-25/cartas/004093.json",
  "primary_image_url": "/legajos/legajo-25/images/052_127.JPG"
}