{
  "legajo_id": "14",
  "id_carta": "1919",
  "order_in_legajo": 19,
  "signatura": "029:2423",
  "nombre_carta": "Carta de Nicolau de Montanyans y Togores a Persona desconocida",
  "fecha_original": "23 de mayo de 1632",
  "lugar": "Mallorca",
  "remitente": "Nicolau de Montanyans y Togores",
  "destinatario": "Persona desconocida",
  "temas": [],
  "idioma": "",
  "resumen": "",
  "modernizada": [
    "Esta serà sols per a respondré a la de v. m. de 10 del present i com el que v. m. envia a demanar de llimones per aquest any no n'hi ha, d'oli de mata el Sr. don Juan Sunyer li n'envia, jo pensa quan n'hi ha en Mallorca per l'any que ve l'escriurem amb abundància amb les sobrassades que na Beatriu li envia n'hi he posades de les que he tingudes muntonec. Don Joan Miquel se n'és carregat i les aigües i tot el {ESP. damés} que v. m. demana que si cregui qual esta terra [?] miraria. Per ara no puc ser més llarg, que acaben la juraria i tenim de fer testament i no tinc cap per a posar les coses com convenen. D'aquí a quatre dies escriuré llarg i satisfaré a mes obligacions amb tot siguin moltes que així les reconec per la mercè que v. m. me fa en les sues. Guardi Nostre Senyor a v. m. com pot. Mallorca a 23 de maig 1632. . Nicolau de Montanyans i Togores Transcripción literal"
  ],
  "literal": [
    "1. Esta sera sols per a respondre a la de V.m. de 102. del pnt y com lo que V.m. envia a demanar de3. llimones per aquest añy no nia de oli de mata 4. lo Sr. don Juan Sunyer lin envia jo pensa quant5. nia en mallca per lo añy qui ve lon scriurem6. ab abundantia en las sobresadas que na beatriu7. li envia ni eposades de las que he tingudes mon=8. tonech don Juan Michel se nes carragat y las ay9. guas y tot lo dames que V.m. demana que10. si creya qual esta terra [?] miraria per11. are no puch ser mes llarch que acaban la12. juraria y tenim de fer testament y no tinch13. cap per aposar las cosas com convenen de14. aqui a quatre dias escriure llarch y satisfare15. a mas obligations ab tot sian moltas que axi16. las regonesch per la merce que V.m. me fa17. en las suas Gde nre señor a V.m. com pot18. Mallca a 23 de Maig 163219. Nº de Montañans20. y togores [☞]"
  ],
  "imagenes": [
    {
      "filename": "029:2423.JPG",
      "original_url": "http://santacilia.info/intranet2/img/Legajo14/029:2423.JPG",
      "url": "/legajos/legajo-14/images/029:2423.JPG"
    }
  ],
  "has_images": true,
  "primary_image": "029:2423.JPG",
  "warnings": [],
  "raw_source": "raw/legajos/legajo-14/cartas/001919.json",
  "primary_image_url": "/legajos/legajo-14/images/029:2423.JPG"
}