{
  "legajo_id": "23",
  "id_carta": "3771",
  "order_in_legajo": 27,
  "signatura": "042:3183a.JPG",
  "nombre_carta": "Carta de Magdalena Gallo i Oliver a Pedro Santacilia y Pax",
  "fecha_original": "25 de junio de 1630",
  "lugar": "Mallorca",
  "remitente": "Magdalena Gallo i Oliver",
  "destinatario": "Pedro Santacilia y Pax",
  "temas": [],
  "idioma": "",
  "resumen": "",
  "modernizada": [
    "V. m. perdoni la tardança he tengut en respondre a la de v. m., que la falta és per haver estat ma mare sens una hora de salut i sangrada quatre vegades sens poder consolar-la de la mort de mon germà. Després d'onze amb s'{ESP. ausència} i prega al senyor que sia per penitència de nostres pecats i puguem tots agrair a v. m. tanta voluntat, que la nostra sempre estarà per a servir a v. m. La senyora tia de v. m. m'ha dit com Nicolau està en Barcelona acomodat amb un cavaller i que si ho volem que v. m. enviarà a dir a v. m. que no convé vinga, puix està acomodat. I v. m. me fa mercè en tenir {ESP. cuidado} què és de nou o enviar-me. Ja jo l'he escrit al senyor Miquel (ara [a] Eivissa), dient-li que no convé vinga, que en Mallorca en dos dies serà perdut; que des d'Eivissa crec escriurà a v. m. el que resoldrà fer. Aquí va la carta per al senyor don Bonaventura de Lanuza en resposta d'ella, que envià amb les còpies de tot, ja que restam molt satisfetes de {ESP. su merced} puix mon germà l'ha deixat i posat en lloc de perquè sempre i ara ha mostrat al seu valor i tot ben ordenat com a bon cavaller de d'{ESP. acá}. Tota la vida tindrem obligació [1§] a tanta caritat i puntualitat amb què s'hagi fet tot el que deixà mon germà, per bé de la sua anima que sia al Cel. I v. m. visqui molts anys i el vegem com desitjam, que sia per servir a Déu Nostre Senyor i el guardi infinits anys. De Mallorca, als vint-i-cinc de juny. Magdalena Gallo Mallorca, 25 juny 1630Senyora Magdalena Gallo, resposta. Transcripción literal"
  ],
  "literal": [
    "1. V.m perdona la terdanca e tengut en respondra2. a la de V.m. q la falta és per aver estat Ma ma 3. ra cens una ora de callut y cengrada quatra4. yveiades cens porer a concollarca da la mort de5. mon jarma despres de onsa anse de ausencia 6. y preia al ceinor q cia per penitencia da nos7. tros pecast y puiam tost agrair á Vm tanta vol8. (l)untat q la nostra cenpra estara per acervir9. a Vm. /. La ceiora tie de Vm me adit com nicola10. u esta an barcelona acomodat ab un cav11. aller y q ci lo volam q Vm anviara dir12. a Vm qua no conve vinga pusc esta acomo13. dat y Vm ma fa mercet en tanir cuidado q 14. es danou o bliiarma ya go loe eschrit al- 15. ceinor miquel arayvisa[?] dientli qua no16. conve vinga q en mallorcha ab dos dias 17. cara perdut q dende aivisa chrec eschriura18. a Vm lo q resolra fer / achy va la carta- 19. per lo ceinor don bona ventura de llanu20. ca en rasposta della q envia ab las copias21. da tot ja qua restam molt castifetas de su22. mercet pusc mon garma loa dexat y posat23. ab loc de para q cenpra y ara amostrat al24. ceu valor y tot ben ordenat com a bon cav25. aller da ca tota la vida tindrem obliiacio [☞]"
  ],
  "imagenes": [
    {
      "filename": "042:3183a.JPG",
      "original_url": "http://santacilia.info/intranet2/img/Legajo23/042:3183a.JPG",
      "url": "/legajos/legajo-23/images/042:3183a.JPG"
    },
    {
      "filename": "043:3183b.JPG",
      "original_url": "http://santacilia.info/intranet2/img/Legajo23/043:3183b.JPG",
      "url": "/legajos/legajo-23/images/043:3183b.JPG"
    }
  ],
  "has_images": true,
  "primary_image": "042:3183a.JPG",
  "warnings": [],
  "raw_source": "raw/legajos/legajo-23/cartas/003771.json",
  "primary_image_url": "/legajos/legajo-23/images/042:3183a.JPG"
}