{
  "legajo_id": "32",
  "id_carta": "7215",
  "order_in_legajo": 215,
  "signatura": "302:1973.JPG",
  "nombre_carta": "Carta de Pedro Antonio Vidal a Pedro Santacilia y Pax",
  "fecha_original": "26 de octubre de 1666",
  "lugar": "Palermo",
  "remitente": "Pedro Antonio Vidal",
  "destinatario": "Pedro Santacilia y Pax",
  "temas": [],
  "idioma": "",
  "resumen": "",
  "modernizada": [
    "Mi señor don Pedro Agole saber como me halló dentro de la ciudad de Palermo el cual me hallo en dicha ciudad porque mis parientes me embarcaron por fuerza y cuando vue llegado asenté plaza de soldado en la compañía de don Francisco Vintimillas hijo del marques de y rache; v. s. ya sabe que soy su criado y así le suplico me haga favor si acaso conoce algún caballero en esta ciudad de escribirle dos renglones para que yo tenga algún consuelo porque me halló tan afligido no de servir al rey sino por no tener conocimiento ni amparo de ninguna persona y así lo fio de que v. s. obrara como quien es y no como yo merezco. Guarde Dios a v. s. mus. ans. a mi señora doña Leonor y mi señor don Juan y a todos los de casa dará v. s. mus. recados de mi parte Palermo y octubre a 26 de 1666 criado de v. s. que s más bs Pedro Antº. vidal Transcripción literal"
  ],
  "literal": [
    "1. Mi Señor Don Pedro 2. Agole saver como me allo dentro de la 3. ciudad de Palermo el qual me hallo en dha 4. ciudad por que mis parientes me enbarcaron 5. por fuerça y quando vue llegado asente 6. plaza de soldado en la compañia de Don 7. Franco. Vintimillas hijo del Marques de 8. Yrache; VSª. ya save que soi su criado y 9. asi le suplico me aga favor siacaso conoze al10. gun cavallero en esta ciudad de escriville dos 11. renglones para que yo tenga algun con12. suelo porque me allo tan afligido no de servir 13. al rey sino por no tener conoçimiento ni an14. paro de ninguna persona y asi lo fio de 15. q VSª. obrara como quien es y no como 16. yo merezco gde. Dios a VSª. mus. ans. 17. a mi Señora Doña Leonor y mi señor 18. Don Juan y a todos los de casa dara 19. VSª. mus. recados de mi parte Palermo 20. y octubre a 26 de 1666 21. Criado de VSª. q s mas bs 22. Pedro Antº. Vidal [☞]"
  ],
  "imagenes": [
    {
      "filename": "302:1973.JPG",
      "original_url": "http://santacilia.info/intranet2/img/Legajo32/302:1973.JPG",
      "url": "/legajos/legajo-32/images/302:1973.JPG"
    }
  ],
  "has_images": true,
  "primary_image": "302:1973.JPG",
  "warnings": [],
  "raw_source": "raw/legajos/legajo-32/cartas/007215.json",
  "primary_image_url": "/legajos/legajo-32/images/302:1973.JPG"
}