{
  "legajo_id": "9",
  "id_carta": "1126",
  "order_in_legajo": 6,
  "signatura": "289-9-07a",
  "nombre_carta": "Carta de Persona desconocida a Arnau de Santacilia",
  "fecha_original": "fecha sin especificar",
  "lugar": "lugar sin especificar",
  "remitente": "Persona desconocida",
  "destinatario": "Arnau de Santacilia",
  "temas": [],
  "idioma": "",
  "resumen": "",
  "modernizada": [
    "Relación de las municiones que se hallaron en este castillo y de las que se han conducido después de haber entrado en él, son las siguientes: -De pólvora: 89 barriles -De balas: 009 barriles -De cajones: 012 balas -Granadas: 125 -Picos: 013-Zapas: 008 -Cabos de cabría: 003-Serruchos: 003 -Cuerda --Ejes de cañón: 003 Recibí del fariel mayor el día 20: -Pólvora: 027 barriles Más que mandó v. m. el día 20: -Cabos de zapas: 130 Más el día 21 -403 granadas -Cajones de balas: 021 -Zapas: 121 -Palas: 123 Mas de Franca Villa: -Pólvora: 020 barriles -De balas: 016 cajones El día 21 -De cuerda: 003 cargas -De bizcocho: 003 cargas Pólvora en todo son: 131 De balas son: 096 De granadas: 574 [1§] De picos son: 013 De zapas son: 124 De palos son: 123Cabos de cabría son: 003De serruchos: 003 De cuerda: - Ejes de cañón: 003Cabos de zapas: 130 Soldados de muestra: 325 Transcripción literal"
  ],
  "literal": [
    "1. Relacíon delos mulisiones q se allaron en este castillo 2. ydelos quesean condusido despues de aber entrado enel 3. son las síguentes= 4. Depolbora 089 Bariles [☞]"
  ],
  "imagenes": [
    {
      "filename": "289-9-07a.jpg",
      "original_url": "http://santacilia.info/intranet2/img/Legajo09/289-9-07a.jpg",
      "url": "/legajos/legajo-09/images/289-9-07a.jpg"
    },
    {
      "filename": "290-9-07b.jpg",
      "original_url": "http://santacilia.info/intranet2/img/Legajo09/290-9-07b.jpg",
      "url": "/legajos/legajo-09/images/290-9-07b.jpg"
    }
  ],
  "has_images": true,
  "primary_image": "289-9-07a.jpg",
  "warnings": [],
  "raw_source": "raw/legajos/legajo-09/cartas/001126.json",
  "primary_image_url": "/legajos/legajo-09/images/289-9-07a.jpg"
}