{
  "legajo_id": "11",
  "id_carta": "1395",
  "order_in_legajo": 144,
  "signatura": "274:5252e.JPG",
  "nombre_carta": "Carta de Pedro Juan de la Guardia a Francisco Forteza",
  "fecha_original": "19 de marzo de 1644",
  "lugar": "Valencia",
  "remitente": "Pedro Juan de la Guardia",
  "destinatario": "Francisco Forteza",
  "temas": [],
  "idioma": "",
  "resumen": "",
  "modernizada": [
    "Ya v. m. sabe las obligaciones que me corren de servir a v. m. y vienen a ser mayores cuando muestra v. m. tener particular gusto en que acuda al negocio del señor don Jaime Anglada que le aseguro con toda verdad que he hecho por el lo que pudiera por v. m. este caballero ha querido perder voluntariamente, pero con todo hemos de procurar que el hierro que ha hecho no lo pague con su hacienda. Sobre la materia hemos conferido largamente el conde Marradas y yo me remito a su carta y del estado que eso tiene a la que escribo el señor don Vicente que cierto lo deseo con tanta eficacia que es forzoso hacerlo posible para que su señoría quede servido y v. m. gustoso. El licenciado Pedro Juan de la Guardia Sr. don Juan Francisco Forteza Sr. mío, novedad me ha hecho siendo v. m. tan mío el haber estado en este lugar y no haberme lo saber. El duque de Arcos me ha dicho como ha tenido orden de su majestad para hacer detener a v. m. su exelentísima es tan honrador de todos que le suplico se sirva de venirse luego por acá sin embarazo ninguno, pues yo de mi parte haré todos los oficios que debo a servidor de v. m. para que aquí se ajusten las materias como v. m. y sus servidores deseamos, a quien guarde Dios muchos años. Valencia 19 Marzo 1644. Don Crisanto Sorell Transcripción literal"
  ],
  "literal": [
    "1. Ja VMd sabe las obligaciones que me corren de 2. servir a VMd y vienen a ser majores quando muestra VMd tener 3. particular gusto en que acuda al negocio del señor don Jaime Anglada 4. que le assiguro con toda verdad que he hecho por el lo que pudiera por 5. VMd este cavallero ha querido perder voluntariamente pero con 6. todo hemos de procurar que el hierro que ha echo no lo pague con su 7. hazienda sobre la materia hemos conferido largamente el sr. Conde 8. Marradas y jo me remito a su carta y del estado que esso tiene 9. a la que escrivo el señor don Vicente que cierto lo deseo con tanta eficatia que 10. es forçoso hacerlo possible paraque su señoria quede servido y VMd 11. gustoso. 12. El licenciado Pedro Juan de la Guardia13. [^Sr. don Juan Fco. Forteza^]14. [otra carta en la misma hoja]15. Sr. mio novedad me ha echo siendo VM tan sr. 16. mio el haver estado en este lugar y no haverme lo saber . 17. El sr. Duque de Arcos me ha dicho como ha tenido orden 18. de su Magma es tan 19. onrador de todos que le suppo se sirva de venir se luego 20. por aca sin embaraso niguno pues jo de mi parte are 21. todos los oficios que devo a servidor de VM para que 22. aqui se ajusten las materias como VM y sus servidores 23. deseamos a quien gd Dios muchos años Valensia 19 24. março 1644. 25. Don Crisanto Sorell [☞]"
  ],
  "imagenes": [
    {
      "filename": "274:5252e.JPG",
      "original_url": "http://santacilia.info/intranet2/img/Legajo11/274:5252e.JPG",
      "url": "/legajos/legajo-11/images/274:5252e.JPG"
    }
  ],
  "has_images": true,
  "primary_image": "274:5252e.JPG",
  "warnings": [],
  "raw_source": "raw/legajos/legajo-11/cartas/001395.json",
  "primary_image_url": "/legajos/legajo-11/images/274:5252e.JPG"
}