{
  "legajo_id": "11",
  "id_carta": "1323",
  "order_in_legajo": 92,
  "signatura": "160:5183.JPG",
  "nombre_carta": "Carta de Juan Bautista Brondo a Pedro Santacilia y Pax",
  "fecha_original": "4 de agosto de 1643",
  "lugar": "Madrid",
  "remitente": "Juan Bautista Brondo",
  "destinatario": "Pedro Santacilia y Pax",
  "temas": [],
  "idioma": "",
  "resumen": "",
  "modernizada": [
    "Sr. don Pedro Sante Silia recibí la de v. m. de 10 del pasado y en ella he visto la merced que me ha hecho en haber hecho pagar a Miguel Sancho lo que a que se le debía de que quedo con el agradesimien to que es rason, siempre sea v. m. obligando de mérito a sus servidores y onrándoles en todas ocasiones y en particular a mi que me prescio de serlo deseando me mande muchas cosas de su servicio en Madrid y agosto 4 de 1643 Juan Bapta Brondo [1§] Transcripción literal"
  ],
  "literal": [
    "1. [^sr. don Pedro Sante Silia^] 2. Recibi la de VM de 10 del pasado y en hella 3. he visto la merced que me ha hecho en haver 4. echo pagar a Miguel Sancho lo que a qui se le 5. devia de que quedo con el hagradesimien 6. to que es rason, siempre sea VM obbligan 7. do de merito a sus servidores y onrandoles 8. en todas ocasiones y en particular a mi que 9. me prescio de serlo deseando me mande mu 10. chas cosas de su servisio en Madrid y agosto 11. 4 de 1643 12. Juan Bapta Brondo [☞]"
  ],
  "imagenes": [
    {
      "filename": "160:5183.JPG",
      "original_url": "http://santacilia.info/intranet2/img/Legajo11/160:5183.JPG",
      "url": "/legajos/legajo-11/images/160:5183.JPG"
    }
  ],
  "has_images": true,
  "primary_image": "160:5183.JPG",
  "warnings": [],
  "raw_source": "raw/legajos/legajo-11/cartas/001323.json",
  "primary_image_url": "/legajos/legajo-11/images/160:5183.JPG"
}