{
  "legajo_id": "19",
  "id_carta": "7575",
  "order_in_legajo": 141,
  "signatura": "136_cg57a.JPG",
  "nombre_carta": "Carta de Pedro Santacilia y Pax a Pedro Santacilia y Pax",
  "fecha_original": "fecha sin especificar",
  "lugar": "lugar sin especificar",
  "remitente": "Pedro Santacilia y Pax",
  "destinatario": "Pedro Santacilia y Pax",
  "temas": [],
  "idioma": "",
  "resumen": "",
  "modernizada": [
    "Excelentísimo señordon Pedro Santacilia y Pax Supca. a v. e. se [?] valerle con el Inqor. general para que mande dos cosas Launa, que se haiga originalmente al Supº. de la Inqon. el proceso que se le ha hecho por el Inqor. de Mallª. para que se vea que no hay cosa probada contra el, y la pasión, y extorsiones que ha avido, que se hechan de ver del mismo proceso la otra, que mande al Inqor. de Mallª. que supuesto no puede continuar la ejecución, que tiene començada en los bie-nes del Supte. por estar de manifiesto algunos años ha por elpatrimonio real de Mallª. y no sirve la pretensión delInqor. en la Competencia, que ha firmado sian de gastos, y se con-sumen los bienes, desista reintegrando al patrimonio, quecon esto confía se pondrán las [?] en mejor estado, y recibiraparticular md. de las manos de v. e. don Pedro Santacilia y Pax Transcripción literal"
  ],
  "literal": [
    "1. Exmo. Señor 2. Don Pedro SantaCilia y Pax = Supca. a V. Exª. se ?? 3. valerle con el Sr. Inqor. General para que mande dos cajas = la4. una, que se aiga originalmente al Supº. dela Inqon. el processo5. que sele ha hecho por el Inqor. de Mallª. paraque se vea6. que no ay cosa provada contra el, y la passion, y extorsiones 7. que ha avido, que se hechan de ver del mismo proceso = 8. La otra, que mande al Inqor. de Mallª. que supuesto no 9. puede continuar la execucion, que tiene començada en los bie-10. nes del Supte. por estar de manifiesto algunos años ha por el 11. patrimonio Real de Mallª. y no sirve la pretension de dho 12. Inqor. en la competencia, que ha firmado fian de gastos, y se con-13. sumen los bienes, que desista reintegrado al patrimonio, que 14. con esto confia se pondran las cosas en mejor estado, y recibira 15. particular md. de las manos de V. Exª. [☞]"
  ],
  "imagenes": [
    {
      "filename": "136_cg57a.JPG",
      "original_url": "http://santacilia.info/intranet2/img/Legajo19/136_cg57a.JPG",
      "url": "/legajos/legajo-19/images/136_cg57a.JPG"
    },
    {
      "filename": "137_cg57b.JPG",
      "original_url": "http://santacilia.info/intranet2/img/Legajo19/137_cg57b.JPG",
      "url": "/legajos/legajo-19/images/137_cg57b.JPG"
    }
  ],
  "has_images": true,
  "primary_image": "136_cg57a.JPG",
  "warnings": [],
  "raw_source": "raw/legajos/legajo-19/cartas/007575.json",
  "primary_image_url": "/legajos/legajo-19/images/136_cg57a.JPG"
}